bim/__init__.py
bim/attributions.py
bim/metrics.py
bim/pipeline_test.py
bim/resnet_model_wrapper.py
bim/run_tcav.py
bim-0.4.dist-info/LICENSE
bim-0.4.dist-info/METADATA
bim-0.4.dist-info/WHEEL
bim-0.4.dist-info/top_level.txt
bim-0.4.dist-info/RECORD
