Metadata-Version: 2.1
Name: bim
Version: 0.4
Summary: Benchmark interpretability methods.
Home-page: https://github.com/google-research-datasets/bim
Author: Google Inc.
Author-email: opensource@google.com
License: Apache 2.0
Platform: UNKNOWN
Requires-Dist: numpy
Requires-Dist: tensorflow
Requires-Dist: Pillow (>=6.0.0)
Requires-Dist: tcav (>=0.2.1)
Requires-Dist: saliency (>=0.0.2)
Requires-Dist: Cython (>=0.29.12)
Requires-Dist: pycocotools (>=2.0.0)
Requires-Dist: scikit-learn (>=0.20.3)
